pyspell/__init__.py
pyspell/bktree.py
pyspell/checker.py
pyspell/updateDict.py
pythonspell-1.21.dist-info/LICENSE
pythonspell-1.21.dist-info/METADATA
pythonspell-1.21.dist-info/WHEEL
pythonspell-1.21.dist-info/top_level.txt
pythonspell-1.21.dist-info/RECORD
