Metadata-Version: 2.1
Name: pythonspell
Version: 1.21
Summary: A simple python spellchecker built on BK Trees and Damerau Levenshtein distance
Home-page: https://github.com/AidanJSmith/Pythonspell
Author: Aidan Smith
Author-email: 100023755@mvla.net
License: MIT
Keywords: spelling corrector autocorrect
Platform: UNKNOWN
